{
    "name": "Samus - Soft Peach",
    "description": "Art by bluethebone",
    "authors": [
        {
            "name": "Silvy",
            "id": "1135310796059070515"
        }
    ],
    "plus": {
       "version": 0,
       "mentionLineColor": "#F0CBB6",
       "iconpack": "rosiecord-plumpy"
    },
    "semanticColors": {
        "HEADER_PRIMARY": ["#F0CBB6"],
        "HEADER_SECONDARY": ["#F3D6C4"],
        "TEXT_NORMAL": ["#ffffff"],
        "TEXT_PRIMARY": ["#F4DCC4"],
        "TEXT_MUTED": ["#F0CBB6"],
        "INTERACTIVE_NORMAL": ["#F0CBB6"],
        "INTERACTIVE_HOVER": ["#F0CBB6"],
        "INTERACTIVE_ACTIVE": ["#F4DCC4"],
        "INTERACTIVE_MUTED": ["#F0CBB6"],
        "BACKGROUND_PRIMARY": ["#141414"],
        "BACKGROUND_SECONDARY": ["#222222"],
        "BACKGROUND_SECONDARY_ALT": ["#222222"],
        "BACKGROUND_TERTIARY": ["#222222"],
        "BACKGROUND_ACCENT": ["#000000"],
        "BACKGROUND_FLOATING": ["#000000"],
        "BACKGROUND_MOBILE_PRIMARY": ["#141414"],
        "BACKGROUND_MOBILE_SECONDARY": ["#222222"],
        "BACKGROUND_NESTED_FLOATING": ["#141414"],
        "BACKGROUND_MENTIONED": ["rgba(240, 203, 183, 0.4)"],
        "BACKGROUND_MESSAGE_HOVER": ["#F0CBB6"],
        "BACKGROUND_MODIFIER_HOVER": ["#141414"],
        "BACKGROUND_MODIFIER_ACTIVE": ["#141414"],
        "BACKGROUND_MODIFIER_SELECTED": ["#141414"],
        "BACKGROUND_MODIFIER_ACCENT": ["#222222"],
        "SCROLLBAR_THIN_THUMB": ["#F0CBB6"],
        "SCROLLBAR_THIN_TRACK": ["transparent"],
        "SCROLLBAR_AUTO_THUMB": ["#F0CBB6"],
        "SCROLLBAR_AUTO_TRACK": ["#F0CBB7"],
        "CHANNEL_TEXT_AREA_PLACEHOLDER": ["#F0CBB6"],
        "CHANNELS_DEFAULT": ["#F0CBB6"],
        "TEXT_LINK": ["#F0CCB6"],
        "TEXT_DANGER": ["#F0CBB8"],
        "KEYBOARD": ["#000000"],
        "CHANNEL_ICON": ["#F0CBB6"],
        "CHAT_BACKGROUND": ["#141414"],
        "REDESIGN_ACTIVITY_CARD_BACKGROUND": ["#000000"],
        "CARD_PRIMARY_BG": ["#141414"],
        "CARD_SECONDARY_BG": ["#222222"],
        "REDESIGN_BUTTON_SECONDARY_BACKGROUND": ["#141414"],
        "BG_BACKDROP": ["#04010173"]
    },
    "rawColors": {
        "PRIMARY_500": "#5289D6",
        "PRIMARY_100": "#5289D6",
        "PRIMARY_200": "#F2A0EB",
        "PRIMARY_230": "#ffffff",
        "PRIMARY_300": "#5289D6",
        "PRIMARY_360": "#F2A0EB",
        "PRIMARY_400": "#5289D6",
        "PRIMARY_600": "#141414",
        "PRIMARY_630": "#000000",
        "PRIMARY_645": "#141414",
        "PRIMARY_660": "#141414",
        "PRIMARY_700": "#141414",
        "PRIMARY_800": "#000000",
        "PLUM_1": "#ffffff",
        "PLUM_3": "#6786CA",
        "PLUM_6": "#6786CA",
        "PLUM_9": "#ffffff",
        "PLUM_10": "#A4A4A4",
        "PLUM_11": "#000000",
        "PLUM_13": "#4C6396",
        "PLUM_17": "#000000",
        "PLUM_18": "#000000",
        "PLUM_19": "#000000",
        "PLUM_20": "#000000",
        "PLUM_22": "#000000",
        "PLUM_24": "#000000",
        "BRAND_260": "#F2A0EB",
        "BRAND_360": "#F2A0EB",
        "BRAND_500": "#5289D6",
        "BRAND_560": "#5289D6",
        "YELLOW_300": "#6786CA",
        "YELLOW_260": "#6786CA",
        "GREEN_600": "#141414",
        "GREEN_360": "#5289D6",
        "RED_400": "#b00b69",
        "WHITE_500": "#f9f1f1"
    },
    "background": {
        "blur": 0,
        "url": "https://cdn.discordapp.com/attachments/1279527650410496071/1279616287336828992/IMG_3482.gif?ex=66d51709&is=66d3c589&hm=e259b6ab9b7dd3edfff8816fb2505281b7bee45a548c26afaf4c22ddafa4cdde&",
        "alpha": 0.7
    },
    "color": "#F0CBB6"
}
