{
    "name": "Silver Wolf",
    "description": "Art by unfairr",
    "authors": [
        {
            "name": "Silvy",
            "id": "1135310796059070515"
        }
    ],
    "plus": {
        "version": 0,
        "mentionLineColor": "#4C2F2D",
        "iconpack": "rosiecord-plumpy"
    },
    "semanticColors": {
        "HEADER_PRIMARY": [
            "#ffffff"
        ],
        "HEADER_SECONDARY": [
            "#ffffff"
        ],
        "TEXT_NORMAL": [
            "#ffffff"
        ],
        "TEXT_PRIMARY": [
            "#ffffff"
        ],
        "TEXT_MUTED": [
            "#ffffff"
        ],
        "INTERACTIVE_NORMAL": [
            "#ecdedc"
        ],
        "INTERACTIVE_HOVER": [
            "#9f6156"
        ],
        "INTERACTIVE_ACTIVE": [
            "#b35f54"
        ],
        "INTERACTIVE_MUTED": [
            "#f8f2f1"
        ],
        "BACKGROUND_PRIMARY": [
            "#a57873"
        ],
        "BACKGROUND_SECONDARY": [
            "#a57873"
        ],
        "BACKGROUND_SECONDARY_ALT": [
            "#a57873"
        ],
        "BACKGROUND_TERTIARY": [
            "#a57873"
        ],
        "BACKGROUND_ACCENT": [
            "#a57873"
        ],
        "BACKGROUND_FLOATING": [
            "#a57873"
        ],
        "BACKGROUND_MOBILE_PRIMARY": [
            "#a57873"
        ],
        "BACKGROUND_MOBILE_SECONDARY": [
            "#a57873"
        ],
        "BACKGROUND_NESTED_FLOATING": [
            "#a57873"
        ],
        "BACKGROUND_MENTIONED": [
            "#a57873"
        ],
        "BACKGROUND_MESSAGE_HOVER": [
            "#a57873"
        ],
        "BACKGROUND_MODIFIER_HOVER": [
            "#a57873"
        ],
        "BACKGROUND_MODIFIER_ACTIVE": [
            "#a57873"
        ],
        "BACKGROUND_MODIFIER_SELECTED": [
            "#a57873"
        ],
        "SCROLLBAR_THIN_THUMB": [
            "#ac8586"
        ],
        "SCROLLBAR_THIN_TRACK": [
            "#c4a7a3"
        ],
        "SCROLLBAR_AUTO_THUMB": [
            "#ac8586"
        ],
        "SCROLLBAR_AUTO_TRACK": [
            "#c5a9a6"
        ],
        "CHANNEL_TEXT_AREA_PLACEHOLDER": [
            "#ffffff"
        ],
        "CHANNELS_DEFAULT": [
            "#ffffff"
        ],
        "TEXT_LINK": [
            "#ffffff"
        ],
        "TEXT_DANGER": [
            "#ffffff"
        ],
        "KEYBOARD": [
            "#a47771"
        ],
        "CHANNEL_ICON": [
            "#ffffff"
        ],
        "CHAT_BACKGROUND": [
            "#a57873"
        ],
        "REDESIGN_ACTIVITY_CARD_BACKGROUND": [
            "#a57873"
        ],
        "CARD_PRIMARY_BG": [
            "#76504b"
        ],
        "CARD_SECONDARY_BG": [
            "#d7aaa3"
        ],
        "REDESIGN_BUTTON_SECONDARY_BACKGROUND": [
            "#a57873"
        ],
        "BG_BACKDROP": [
            "#b35f54"
        ]
    },
    "rawColors": {
        "PRIMARY_500": "#74504b",
        "PRIMARY_100": "#74504b",
        "PRIMARY_200": "#f9f3f2",
        "PRIMARY_230": "#76504b",
        "PRIMARY_300": "#a27670",
        "PRIMARY_360": "#ac8586",
        "PRIMARY_400": "#d1bbbc",
        "PRIMARY_600": "#a27670",
        "PRIMARY_630": "#c1a4a0",
        "PRIMARY_645": "#a47771",
        "PRIMARY_660": "#78514d",
        "PRIMARY_700": "#78514d",
        "PRIMARY_800": "#74504b",
        "PLUM_1": "#78514d",
        "PLUM_3": "#a57873",
        "PLUM_6": "#a27670",
        "PLUM_9": "#c7aaa7",
        "PLUM_10": "#c79f98",
        "PLUM_11": "#c5a9a6",
        "PLUM_13": "#d1bbbc",
        "PLUM_17": "#9f6156",
        "PLUM_18": "#d7aaa3",
        "PLUM_19": "#f8f2f1",
        "PLUM_20": "#f9f3f2",
        "PLUM_22": "#b46053",
        "PLUM_24": "#c5a9a6",
        "BRAND_260": "#c2a5a1",
        "BRAND_360": "#c8aca9",
        "BRAND_500": "#ecdedc",
        "BRAND_560": "#c4a7a3",
        "YELLOW_300": "#f8f2f1",
        "YELLOW_260": "#a77a75",
        "GREEN_600": "#76504b",
        "GREEN_360": "#c2a5a1",
        "RED_400": "#77504c",
        "WHITE_500": "#c8aca9"
    },
    "background": {
        "blur": 0,
        "url": "https://cdn.discordapp.com/attachments/1279964818203476149/1279968954814697566/image.png?ex=66d65f7b&is=66d50dfb&hm=54f803c6f8e98b94e5d2a19b6749977a5db43f723b0520c51748d96a8802081a&",
        "alpha": 0.7
    },
    "color": "#4C2F2D"
}